<annotation>
	<folder>images</folder>
	<filename>goose-mugshot-0038.jpg</filename>
	<path>C:\Users\Steggie\git\goose-dataset-master\images\goose-mugshot-0038.jpg</path>
	<source>
		<database>Unknown</database>
	</source>
	<size>
		<width>800</width>
		<height>533</height>
		<depth>3</depth>
	</size>
	<segmented>0</segmented>
	<object>
		<name>goose-head</name>
		<pose>Unspecified</pose>
		<truncated>0</truncated>
		<difficult>0</difficult>
		<bndbox>
			<xmin>145</xmin>
			<ymin>38</ymin>
			<xmax>752</xmax>
			<ymax>429</ymax>
		</bndbox>
	</object>
</annotation>
